Metadata-Version: 2.1
Name: Mbedder
Version: 0.0.1
Summary: Mbedder: A pytorch powered framework for seemlessly adding contextual text embeddings  from pretrained models
Home-page: https://github.com/monkeysforever/Mbedder
Author: Randeep Ahlawat
Author-email: ahlawat.randeep@gmail.com
License: UNKNOWN
Platform: UNKNOWN
Classifier: Programming Language :: Python :: 3.6
Classifier: License :: OSI Approved :: MIT License
Classifier: Topic :: Scientific/Engineering :: Artificial Intelligence
Classifier: Operating System :: Unix
Classifier: Intended Audience :: Science/Research
Requires-Python: >=3.6
